{
    "AA_Components_Test_Cases": [
        "47024",
        "47025",
        "84155",
        "83810",
        "47021",
        "47020",
        "47019",
        "47018",
        "47017",
        "47015",
        "47014",
        "47016",
        "46988",
        "46972",
        "47013",
        "47012",
        "46984",
        "46993",
        "47011",
        "47010",
        "47009",
        "47036",
        "47026",
        "47034",
        "46994",
        "87978",
        "87977",
        "87976",
        "87975",
        "46970",
        "46975",
        "46976",
        "46979",
        "46981",
        "46982",
        "46977",
        "46995",
        "47008",
        "47038",
        "47007",
        "47006",
        "47005",
        "47004",
        "46980",
        "47002",
        "47003",
        "46985",
        "47031",
        "47030",
        "47022",
        "47001",
        "46966",
        "46965",
        "47000",
        "46996",
        "46992",
        "47037",
        "46991",
        "46964",
        "46986",
        "46999",
        "46978",
        "47035",
        "47027",
        "46998",
        "46997",
        "46963",
        "46962"
    ],
    "Areva_Test_Cases": [
        "48378",
        "48380",
        "48377",
        "48376",
        "48379"
    ],
    "BP_Test_Cases": [
        "81797",
        "51677",
        "51734",
        "51517",
        "51582",
        "51594",
        "54635",
        "51518"
    ],
    "Brazilian_Navy_Seafloor_Test_Cases": [
        "55636",
        "55635",
        "55632",
        "55631"
    ],
    "UX-Analyze_Advanced_Test_Cases": [
        "76239",
        "57508",
        "55666",
        "90008",
        "90007",
        "90006",
        "86487",
        "86474",
        "85514",
        "84641",
        "83675",
        "82555",
        "82089",
        "82085",
        "82083",
        "81942",
        "81923",
        "81914",
        "81913",
        "81911",
        "81908",
        "81891",
        "81882",
        "81876",
        "81874",
        "79972",
        "79969",
        "79962",
        "79794",
        "76265",
        "76225",
        "73685",
        "56181",
        "56273",
        "56255",
        "56239",
        "57962",
        "57961",
        "57959",
        "57954",
        "72194",
        "72048",
        "58823",
        "58815",
        "77450",
        "77190",
        "77189",
        "76237",
        "76236",
        "76234",
        "76060",
        "75003",
        "74991",
        "74940",
        "74935",
        "74932",
        "74547",
        "74147",
        "74143",
        "81921",
        "57951",
        "85506",
        "55630",
        "55547",
        "55542",
        "57472",
        "57473",
        "57474",
        "57503",
        "55962",
        "57504"
    ],
    "Gravity_Gradiometry_Test_Cases": [
        "46899",
        "46913",
        "46893",
        "46889",
        "46891",
        "46888",
        "46890",
        "46886",
        "46894",
        "46895",
        "46892",
        "46916",
        "46906",
        "46907",
        "46905",
        "46898",
        "46903",
        "46902",
        "46900",
        "46914",
        "46912",
        "46910",
        "46911",
        "46909",
        "46919",
        "46918"
    ],
    "RTX_Test_Cases": [
        "72839",
        "46943",
        "46942",
        "46941",
        "72964",
        "72821",
        "72828",
        "72830",
        "72835"
    ],
    "SAGAX_Test_Cases": [
        "55935",
        "55923",
        "55920",
        "55912",
        "55915",
        "55911"
    ],
    "ORNL_Test_Cases": [
        "87423",
        "87405"
    ],
    "Shell_Test_Cases": [
        "81790",
        "55194",
        "55562",
        "48361",
        "48362",
        "48360",
        "48373",
        "48372",
        "48366",
        "48368",
        "48367",
        "48369",
        "48355",
        "48356",
        "48357"
    ],
    "USGS_Custom_Tools_Test_Cases": [
        "76522",
        "76517",
        "46935",
        "46937",
        "46936",
        "46930",
        "46932",
        "46934",
        "46929",
        "46927",
        "46928",
        "46924",
        "46923",
        "46925",
        "46931"
    ],
    "YPF_Custom_Tools_Test_Cases": [
        "87032",
        "87035",
        "87031"
    ],
    "DeBeers_Custom_Projection_Tool_Test_Cases": [],
    "DeBeers_Classification_Tool_Test_Cases": [
        "72036",
        "55627",
        "55168"
    ],
    "Hudbay_Test_Cases": [
        "88020",
        "88019",
        "88018",
        "88009",
        "88008",
        "87986",
        "87985",
        "87982"
    ],
    "MTA_Crust_Thickness_Test_Cases": [
        "46938",
        "46940",
        "46939"
    ],
    "VALE_DIPM_Test_Cases": [
        "85817",
        "85914",
        "85808",
        "85899",
        "85905",
        "85911",
        "85804",
        "85910",
        "85805",
        "85799"
    ]
}